ciscoaxlJFK/__init__.py
ciscoaxlJFK/__int__.py
ciscoaxlJFK/axl.py
ciscoaxlJFK-0.0.2.dist-info/LICENSE
ciscoaxlJFK-0.0.2.dist-info/METADATA
ciscoaxlJFK-0.0.2.dist-info/WHEEL
ciscoaxlJFK-0.0.2.dist-info/top_level.txt
ciscoaxlJFK-0.0.2.dist-info/RECORD
