Metadata-Version: 2.1
Name: ciscoaxlJFK
Version: 0.0.2
Summary: custom AXL/SQL Package
Home-page: https://github.com/
Author: JFK
Author-email: info@jfk.rocks
License: UNKNOWN
Platform: UNKNOWN
Requires-Python: >=3.8
License-File: LICENSE
Requires-Dist: zeep (==3.4.0)
Requires-Dist: urllib3 (==1.23)
Requires-Dist: requests (==2.22.0)
Requires-Dist: six (==1.12.0)
